{
  "aacDnsPrePinning": true,
  "accessibilityFeatureAssistiveTouch": 0,
  "accessibilityFeatureGrayscaleDisplay": 0,
  "accessibilityFeatureInvertColors": 0,
  "accessibilityFeatureVoiceOver": 0,
  "accessibilityFeatureZoom": 0,
  "additionalResources": [],
  "allowApplicationLog": false,
  "audioControlEnabled": true,
  "audioMute": false,
  "audioSetVolumeLevel": false,
  "audioVolumeLevel": 25,
  "allowBrowsingBackForward": false,
  "allowCustomDownUploadLocation": false,
  "allowDeveloperConsole": false,
  "allowDictation": false,
  "allowDictionaryLookup": false,
  "allowDisplayMirroring": false,
  "allowedDisplayBuiltin": true,
  "allowedDisplayBuiltinEnforce": true,
  "allowedDisplayBuiltinExceptDesktop": true,
  "allowedDisplaysIgnoreFailure": false,
  "allowedDisplaysMaxNumber": 1,
  "allowDownloads": true,
  "allowDownUploads": true,
  "allowFind": true,
  "allowFlashFullscreen": false,
  "allowiOSBetaVersionNumber": 26,
  "allowiOSVersionNumberMajor": 13,
  "allowiOSVersionNumberMinor": 0,
  "allowiOSVersionNumberPatch": 0,
  "allowMacOSVersionNumberCheckFull": false,
  "allowMacOSVersionNumberMajor": 11,
  "allowMacOSVersionNumberMinor": 0,
  "allowMacOSVersionNumberPatch": 0,
  "allowOpenAndSavePanel": false,
  "allowPDFPlugIn": false,
  "allowPDFReaderToolbar": false,
  "allowPreferencesWindow": false,
  "allowPrint": false,
  "allowQuit": true,
  "allowShareSheet": false,
  "allowScreenCapture": false,
  "allowScreenSharing": false,
  "allowSiri": false,
  "allowSpellCheck": false,
  "allowSwitchToApplications": false,
  "allowUploads": false,
  "allowUploadsiOS": false,
  "allowUserAppFolderInstall": false,
  "allowVirtualMachine": false,
  "allowWindowCapture": false,
  "allowWlan": false,
  "autoQuitApplications": true,
  "backgroundOpenSEBConfig": false,
  "batteryChargeThresholdCritical": 0.1,
  "batteryChargeThresholdLow": 0.2,
  "blockPopUpWindows": false,
  "blockScreenShotsLegacy": false,
  "browserConnectionErrorReload": false,
  "browserMediaAutoplay": true,
  "browserMediaAutoplayAudio": true,
  "browserMediaAutoplayVideo": true,
  "browserMediaCaptureCamera": false,
  "browserMediaCaptureMicrophone": false,
  "browserMediaCaptureScreen": false,
  "browserShowFileSystemElementPath": true,
  "browserUserAgent": "",
  "browserUserAgentiOS": 0,
  "browserUserAgentiOSCustom": "",
  "browserUserAgentMac": 0,
  "browserUserAgentMacCustom": "",
  "browserUserAgentWinDesktopMode": 0,
  "browserUserAgentWinDesktopModeCustom": "",
  "browserUserAgentWinTouchMode": 0,
  "browserUserAgentWinTouchModeCustom": "",
  "browserUserAgentWinTouchModeIPad": "Mozilla/5.0 (iPad; CPU OS 18_3 like Mac OS X) AppleWebKit/605.1.15 (KHTML, like Gecko) Version/18.3 Mobile/15E148 Safari/605.1.15",
  "browserViewMode": 0,
  "browserWindowAllowAddressBar": false,
  "browserWindowAllowReload": true,
  "browserWindowShowURL": 0,
  "browserWindowTitleSuffix": "",
  "browserWindowWebView": 2,
  "browserWindowWebViewClassicHideDeprecationNote": false,
  "chooseFileToUploadPolicy": 0,
  "clipboardPolicy": 2,
  "configKeySalt": {
    "__data__": ""
  },
  "configFileCreateIdentity": false,
  "configFileEncryptUsingIdentity": false,
  "createNewDesktop": true,
  "defaultPageZoomLevel": 1,
  "defaultTextZoomLevel": 1,
  "detectAccessibilityApps": true,
  "detectStoppedProcess": true,
  "displayAlwaysOn": true,
  "downloadAndOpenSebConfig": true,
  "downloadDirectoryOSX": "~/Downloads",
  "downloadDirectoryWin": "Downloads",
  "downloadFileTypes": [],
  "downloadPDFFiles": false,
  "embeddedCertificates": [],
  "enableAppSwitcherCheck": true,
  "enableBrowserWindowToolbar": false,
  "enableChromeNotifications": false,
  "enableCursorVerification": true,
  "enableFindPrinter": false,
  "enableJava": false,
  "enableJavaScript": true,
  "enableLogging": true,
  "enableMiddleMouse": false,
  "enablePlugIns": true,
  "enablePrivateClipboard": true,
  "enablePrivateClipboardMacEnforce": true,
  "enableSebBrowser": true,
  "enableSessionVerification": true,
  "enableScreenProctoring": false,
  "enableScrollLock": true,
  "enableURLContentFilter": false,
  "enableURLFilter": false,
  "enableWindowsUpdate": false,
  "enableEsc": true,
  "enableCtrlEsc": false,
  "enableAltEsc": false,
  "enableAltMouseWheel": false,
  "enableAltTab": true,
  "enableAltF4": false,
  "enablePrintScreen": false,
  "enableRightMouse": true,
  "enableRightMouseMac": false,
  "enableStartMenu": false,
  "enableF1": true,
  "enableF2": true,
  "enableF3": true,
  "enableF4": true,
  "enableF5": true,
  "enableF6": true,
  "enableF7": true,
  "enableF8": true,
  "enableF9": true,
  "enableF10": true,
  "enableF11": true,
  "enableF12": true,
  "enableZoomPage": true,
  "enableZoomText": false,
  "examKeySalt": {
    "__data__": ""
  },
  "examSessionClearCookiesOnEnd": true,
  "examSessionClearCookiesOnStart": true,
  "examSessionReconfigureAllow": false,
  "examSessionReconfigureConfigURL": "",
  "hashedAdminPassword": "",
  "hashedQuitPassword": "",
  "hideBrowserWindowToolbar": false,
  "hideWiFiControls": false,
  "hookKeys": true,
  "forceAppFolderInstall": true,
  "ignoreQuitPassword": false,
  "insideSebEnableChangeAPassword": false,
  "insideSebEnableEaseOfAccess": false,
  "insideSebEnableLockThisComputer": false,
  "insideSebEnableLogOff": false,
  "insideSebEnableNetworkConnectionSelector": false,
  "insideSebEnableShutDown": false,
  "insideSebEnableStartTaskManager": false,
  "insideSebEnableSwitchUser": false,
  "insideSebEnableVmWareClientShade": false,
  "jitsiMeetAudioMuted": false,
  "jitsiMeetAudioOnly": false,
  "jitsiMeetEnable": false,
  "jitsiMeetFeatureFlagChat": false,
  "jitsiMeetFeatureFlagCloseCaptions": false,
  "jitsiMeetFeatureFlagDisplayMeetingName": false,
  "jitsiMeetFeatureFlagRaiseHand": false,
  "jitsiMeetFeatureFlagRecording": false,
  "jitsiMeetFeatureFlagTileView": false,
  "jitsiMeetReceiveAudio": false,
  "jitsiMeetReceiveVideo": false,
  "jitsiMeetRoom": "",
  "jitsiMeetSendAudio": true,
  "jitsiMeetSendVideo": true,
  "jitsiMeetServerURL": "",
  "jitsiMeetSubject": "",
  "jitsiMeetToken": "",
  "jitsiMeetUserInfoAvatarURL": "",
  "jitsiMeetUserInfoDisplayName": "",
  "jitsiMeetUserInfoEMail": "",
  "jitsiMeetVideoMuted": false,
  "killExplorerShell": false,
  "logDirectoryOSX": "",
  "logDirectoryWin": "",
  "logLevel": 3,
  "lockdownModePolicy": 0,
  "logSendingRequiresAdminPassword": false,
  "mainBrowserWindowHeight": "100%",
  "mainBrowserWindowPositioning": 1,
  "mainBrowserWindowWidth": "100%",
  "minMacOSVersion": 9,
  "mobileAllowInlineMediaPlayback": true,
  "mobileAllowPictureInPictureMediaPlayback": false,
  "mobileAllowQRCodeConfig": false,
  "mobileAllowSingleAppMode": false,
  "mobileCompactAllowInlineMediaPlayback": false,
  "mobileEnableGuidedAccessLinkTransform": false,
  "mobileEnableASAM": true,
  "mobileEnableModernAAC": false,
  "mobileSleepModeLockScreen": true,
  "mobileShowSettings": false,
  "mobileShowEditConfigShortcutItem": true,
  "mobileStatusBarAppearance": 1,
  "mobileStatusBarAppearanceExtended": 1,
  "mobileSupportedFormFactorsCompact": true,
  "mobileSupportedFormFactorsNonTelephonyCompact": true,
  "mobileSupportedFormFactorsRegular": true,
  "mobileSupportedScreenOrientationsCompactPortrait": true,
  "mobileSupportedScreenOrientationsCompactPortraitUpsideDown": false,
  "mobileSupportedScreenOrientationsCompactLandscapeLeft": true,
  "mobileSupportedScreenOrientationsCompactLandscapeRight": true,
  "mobileSupportedScreenOrientationsRegularPortrait": true,
  "mobileSupportedScreenOrientationsRegularPortraitUpsideDown": true,
  "mobileSupportedScreenOrientationsRegularLandscapeLeft": true,
  "mobileSupportedScreenOrientationsRegularLandscapeRight": true,
  "mobilePreventAutoLock": true,
  "newBrowserWindowAllowAddressBar": false,
  "newBrowserWindowAllowReload": true,
  "newBrowserWindowByLinkBlockForeign": false,
  "newBrowserWindowByLinkHeight": "100%",
  "newBrowserWindowByLinkPolicy": 2,
  "newBrowserWindowByLinkPositioning": 2,
  "newBrowserWindowByLinkWidth": "1000",
  "newBrowserWindowNavigation": true,
  "newBrowserWindowShowReloadWarning": false,
  "newBrowserWindowShowURL": 0,
  "openDownloads": false,
  "oskBehavior": 2,
  "permittedProcesses": [],
  "pinEmbeddedCertificates": false,
  "proctoringAIEnable": false,
  "proctoringDetectFaceAngleDisplay": true,
  "proctoringDetectFaceCount": true,
  "proctoringDetectFaceCountDisplay": true,
  "proctoringDetectFacePitch": true,
  "proctoringDetectFaceYaw": true,
  "proctoringDetectTalking": true,
  "proctoringDetectTalkingDisplay": true,
  "prohibitedProcesses": [],
  "proxies": {},
  "proxySettingsPolicy": 0,
  "quitURL": "",
  "quitURLConfirm": true,
  "quitURLRestart": false,
  "raiseHandButtonShow": true,
  "raiseHandButtonAlwaysPromptMessage": false,
  "remoteProctoringViewShow": 0,
  "removeBrowserProfile": true,
  "restartExamPasswordProtected": true,
  "restartExamText": "",
  "restartExamURL": "",
  "restartExamUseStartURL": false,
  "screenSharingMacEnforceBlocked": false,
  "sebConfigPurpose": 0,
  "sebMode": 0,
  "sebServerConfiguration": {},
  "sebServerFallback": false,
  "sebServerFallbackAttemptInterval": 2000,
  "sebServerFallbackAttempts": 5,
  "sebServerFallbackPasswordHash": "",
  "sebServerFallbackTimeout": 30000,
  "sebServerURL": "",
  "sebServiceIgnore": true,
  "sebServicePolicy": 1,
  "sendBrowserExamKey": false,
  "setVmwareConfiguration": false,
  "screenProctoringCacheSize": 500,
  "screenProctoringClientId": "",
  "screenProctoringClientSecret": "",
  "screenProctoringClientSessionId": "",
  "screenProctoringGroupId": "",
  "screenProctoringImageDownscale": 1,
  "screenProctoringImageFormat": 0,
  "screenProctoringImageQuantization": 0,
  "screenProctoringAACCapturePolicy": 2,
  "screenProctoringIndicateHealthAndCaching": false,
  "screenProctoringMetadataActiveAppEnabled": true,
  "screenProctoringMetadataURLEnabled": true,
  "screenProctoringMetadataWindowTitleEnabled": true,
  "screenProctoringServiceURL": "",
  "screenProctoringScreenshotMaxInterval": 5000,
  "screenProctoringScreenshotMinInterval": 1000,
  "showApplicationLogButton": false,
  "showBackToStartButton": true,
  "showInputLanguage": true,
  "showMenuBar": true,
  "showNavigationButtons": false,
  "showProctoringViewButton": true,
  "showQuitButton": true,
  "showReloadButton": true,
  "showReloadWarning": true,
  "showSideMenu": true,
  "showScanQRCodeButton": false,
  "showScrollLockButton": true,
  "showTaskBar": true,
  "showTime": true,
  "startURL": "https://safeexambrowser.org/start",
  "startURLAllowDeepLink": false,
  "startURLAppendQueryParameter": false,
  "systemAlwaysOn": false,
  "tabFocusesLinks": true,
  "taskBarHeight": 40,
  "touchOptimized": false,
  "URLFilterEnable": false,
  "URLFilterEnableContentFilter": false,
  "URLFilterIgnoreList": [],
  "URLFilterMessage": 0,
  "urlFilterRegex": false,
  "urlFilterTrustedContent": true,
  "useAsymmetricOnlyEncryption": false,
  "useTemporaryDownUploadDirectory": false,
  "URLFilterRules": [],
  "zoomAPIKey": "",
  "zoomAudioMuted": false,
  "zoomEnable": false,
  "zoomFeatureFlagChat": false,
  "zoomFeatureFlagCloseCaptions": false,
  "zoomFeatureFlagRaiseHand": false,
  "zoomFeatureFlagTileView": false,
  "zoomMeetingKey": "",
  "zoomReceiveAudio": false,
  "zoomReceiveVideo": false,
  "zoomRoom": "",
  "zoomSDKToken": "",
  "zoomSendAudio": true,
  "zoomSendVideo": true,
  "zoomServerURL": "",
  "zoomSubject": "",
  "zoomToken": "",
  "zoomUserInfoDisplayName": "",
  "zoomUserName": "",
  "zoomVideoMuted": false
}
